designs/control_unit/cu_control_buffer_register.v
`timescale 1ns / 1ps

module CBR (
    memory,
    ctrl_global_halt,
    ctrl_mar_increment,
    next_addr,
    ALU_op,
    C0,
    C1,
    C2,
    C3,
    C4,
    C5,
    C6,
    C7,
    C8,
    C9,
    C10,
    C11,
    C12,
    C13,
    C14,
    C15
);
  input [23:0] memory;
  output ctrl_global_halt;  // C23
  output ctrl_mar_increment;  // C22
  output [1:0] next_addr;  // C21-C20
  output [3:0] ALU_op;  // C19-C16
  output C0, C1, C2, C3, C4, C5, C6, C7, C8, C9, C10, C11, C12, C13, C14, C15;

  assign C0 = memory[0];
  assign C1 = memory[1];
  assign C2 = memory[2];
  assign C3 = memory[3];
  assign C4 = memory[4];
  assign C5 = memory[5];
  assign C6 = memory[6];
  assign C7 = memory[7];
  assign C8 = memory[8];
  assign C9 = memory[9];
  assign C10 = memory[10];
  assign C11 = memory[11];
  assign C12 = memory[12];
  assign C13 = memory[13];
  assign C14 = memory[14];
  assign C15 = memory[15];

  assign ALU_op = memory[19:16];

  assign next_addr = memory[21:20];
  assign ctrl_mar_increment = memory[22];
  assign ctrl_global_halt = memory[23];

endmodule

designs/control_unit/cu_control_memory.v

/* 
* 1 global halt
* 1 MAR self increment
* 2 CAR 
* 1 ALU_enable 
* 3 ALU 
* 16 internal bus
* C2: Control for PC+1
*/
`timescale 1ns / 1ps

module CONTROL_MEMORY (
    car,
    control_word
);
  input wire [6:0] car;             // From CAR
  output reg [23:0] control_word;   // Output Ctrl Signal

  always @(*) begin
    case (car)
      // Instruction
      7'h00: control_word = 24'b00_10_0000_00000000_00000100;  // IF1, 2 PC+1
      7'h01: control_word = 24'b00_10_0000_00000000_00100001;  // IF2, 0 5 
      7'h02: control_word = 24'b00_10_0000_00000000_00010000;  // ID1, 4
      7'h03: control_word = 24'b00_10_0000_01000000_00000000;  // ID2, 14

      // Operand
      7'h04: control_word = 24'b00_01_0000_10000000_00000000;  // FO,   15
      7'h05: control_word = 24'b00_10_0000_00000001_00000000;  // IND1, 8
      7'h06: control_word = 24'b00_01_0000_00000000_00100001;  // IND2, 0 5

      // STORE
      7'h07: control_word = 24'b00_10_0000_00000001_00000000;  // EX, 8
      7'h08: control_word = 24'b00_11_0000_00110000_00000001;  // WB, 0 12 13

      // LOAD
      7'h09: control_word = 24'b00_10_0000_00000000_00000000;  // EX
      7'h0A: control_word = 24'b00_11_0000_00001000_00000000;  // WB, 11

      // ADD
      7'h0B: control_word = 24'b00_10_1000_00000000_11000000;  // EX, 6 7
      7'h0C: control_word = 24'b00_11_1000_00000000_00100000;  // WB

      // SUB
      7'h0D: control_word = 24'b00_10_1001_00000000_11000000;  // EX, 6 7
      7'h0E: control_word = 24'b00_11_1001_00000000_00100000;  // WB

      // MPY
      7'h0F: control_word = 24'b00_10_1010_00000000_11000000;  // EX, 6 7
      7'h10: control_word = 24'b00_11_1010_00000110_00000000;  // WB, 9 10

      // JGZ & JMP
      7'h11: control_word = 24'b00_10_0000_00000000_00000000;  // EX
      7'h12: control_word = 24'b00_11_0000_00000000_00001000;  // WB, 3

      // HALT
      // Stop and reset control word to IF
      7'h13: control_word = 24'b00_10_0000_00000000_00000000;  // EX
      7'h14: control_word = 24'b10_11_0000_00000000_00000000;  // WB, HALT

      // AND
      7'h15: control_word = 24'b00_10_1011_00000000_11000000;  // EX, 6 7
      7'h16: control_word = 24'b00_11_1011_00000010_00000000;  // WB, 9

      // OR
      7'h17: control_word = 24'b00_10_1100_00000000_11000000;  // EX, 6 7
      7'h18: control_word = 24'b00_11_1100_00000010_00000000;  // WB, 9

      // NOT
      7'h19: control_word = 24'b00_10_1101_00000000_01000000;  // EX, 6 7
      7'h1A: control_word = 24'b00_11_1101_00000010_00000000;  // WB, 9

      // SHIFTR
      7'h1B: control_word = 24'b00_10_1110_00000000_11000000;  // EX, 6 7
      7'h1C: control_word = 24'b00_11_1110_00000010_00000000;  // WB, 9

      // SHIFTL
      7'h1D: control_word = 24'b00_10_1111_00000000_11000000;  // EX, 6 7
      7'h1E: control_word = 24'b00_11_1111_00000010_00000000;  // WB, 9
    
      // Implicit Instructions
      
      // NOP
      // Used for completing the instruction cycle.
      // Executed if JGZ is judged false.

      7'h1F: control_word = 24'b00_10_0000_00000000_00000000;  // EX
      7'h20: control_word = 24'b00_11_0000_00000000_00000000;  // WB

      // STOREH
      // Used for storage of high bytes of multiply results.
      // Executed after STORE Operation on MF = 1.
      
      7'h21: control_word = 24'b00_10_0000_00000001_00000000;  // EX1, 8
      7'h22: control_word = 24'b01_10_0000_00110000_00000001;  // WB1, 0 12 13 MAR+1
      7'h23: control_word = 24'b00_10_0000_00000100_00000000;  // EX2，10
      7'h24: control_word = 24'b00_11_0000_00110000_00000001;  // WB2，0 12 13

      default: control_word = 24'b00_11_0000_00000000_00000000;  // Back to zero addr
    endcase
  end

endmodule

designs/control_unit/cu_control_address_register.v
`timescale 1ns / 1ps

// Sequencing Logic & CAR
/*  Sequencing Logic of CAR 
*   10 self increment
*   11 back to 0
*   01 jump 
*   00 nothing
*/
module CAR (
    i_clk,
    i_rst_n,
    i_control_word_car,
    i_ir_data,
    i_ctrl_ZF,
    i_ctrl_NF,
    i_ctrl_MF,
    o_car_data
);

  input wire i_clk;
  input wire i_rst_n;
  input wire [1:0] i_control_word_car;
  input wire [4:0] i_ir_data;  // MSB + IR[3:0]
  input wire i_ctrl_ZF;  // ZF Flag
  input wire i_ctrl_NF;  // NF Flag
  input wire i_ctrl_MF;  // MF Flag
  output reg [6:0] o_car_data;

  // Indicator of indirect cycle requirement
  wire indirect_flag = i_ir_data[4];

  // Indicator of indirect cycle done, default 0.
  reg indirect_done;


  wire [3:0] ir_data = i_ir_data[3:0];

  always @(posedge i_clk or negedge i_rst_n) begin
    if (!i_rst_n) begin
      o_car_data <= 7'h00;
      indirect_done <= 1'b0;
    end else begin
      // indirect at previlige
      if (indirect_flag && !indirect_done) begin
        o_car_data <= 7'h02;
        indirect_done <= 1'b1;
      end else begin
        case (i_control_word_car)
          2'b01: begin  // Jump to execution
            case (ir_data)
              4'd1: begin
                if (i_ctrl_MF) begin
                  o_car_data <= 7'h23;  // STORE & STOREH
                end else begin
                  o_car_data <= 7'h07;  // STORE Only
                end
              end
              4'd2: o_car_data <= 7'h09;  // LOAD
              4'd3: o_car_data <= 7'h0B;  // ADD
              4'd4: o_car_data <= 7'h0D;  // SUB

              4'd5: begin  // JGZ
                if (!i_ctrl_ZF && !i_ctrl_NF) o_car_data <= 7'h11;
                else o_car_data <= 7'h00;
              end
              4'd6: o_car_data <= 7'h11;     // JMP
              4'd7: o_car_data <= 7'h13;     // HALT
              4'd8: o_car_data <= 7'h0F;     // MPY
              4'd9: o_car_data <= 7'h15;     // AND
              4'd10: o_car_data <= 7'h17;    // OR
              4'd11: o_car_data <= 7'h19;    // NOT
              4'd12: o_car_data <= 7'h1B;    // SHIFTR
              4'd13: o_car_data <= 7'h1D;    // SHIFTL
              default: o_car_data <= 7'h00;
            endcase
          end
          2'b10: begin
            o_car_data <= o_car_data + 1;  // Next Micro-instruction
          end
          2'b11: begin
            o_car_data    <= 7'h00;  // Fetch next instruction
            indirect_done <= 1'b0;  // Reset Indirect Flag
          end
          default: o_car_data <= o_car_data;  // Prevent latch
        endcase
      end
    end
  end

endmodule

designs/control_unit/cu_top.v
// The top module of the CU
// Author: LiPtP
// Date: 2025.4.25
// Should be connected to:
// * All internal registers via Internal Bus
// * ALU
// * External Bus

module CU_TOP (
    i_clk,
    i_rst_n,
    i_flags,
    i_ir_data,
    o_alu_op,
    o_ctrl_halt,
    o_IF_stage,
    o_ctrl_mar_increment,
    C0,
    C1,
    C2,
    C3,
    C4,
    C5,
    C6,
    C7,
    C8,
    C9,
    C10,
    C11,
    C12,
    C13,
    C14,
    C15
);

  // External signals

  input i_clk;
  input i_rst_n;
  input [7:0] i_ir_data;
  input [4:0] i_flags;  // ZF, CF, OF, NF, MF 

  output [3:0] o_alu_op;
  output o_ctrl_mar_increment;  // C23
  output o_IF_stage;  // C2
  output o_ctrl_halt;  // C23
  output C0, C1, C2, C3, C4, C5, C6, C7, C8, C9, C10, C11, C12, C13, C14, C15;

  // Internal signals

  wire [ 1:0] next_addr;
  wire [ 6:0] car_data;
  wire [23:0] control_word;


  CAR control_CAR (
      .i_clk(i_clk),
      .i_rst_n(i_rst_n),
      .i_control_word_car(next_addr),
      .i_ir_data({i_ir_data[7],i_ir_data[3:0]}),
      .i_ctrl_ZF(i_flags[4]),
      .i_ctrl_NF(i_flags[1]),
      .i_ctrl_MF(i_flags[0]),
      .o_car_data(car_data)
  );

  CONTROL_MEMORY control_memory (
      .car(car_data),
      .control_word(control_word)
  );

  CBR control_CBR (
      .memory(control_word),
      .ctrl_global_halt(o_ctrl_halt),
      .ctrl_mar_increment(o_ctrl_mar_increment),
      .next_addr(next_addr),
      .ALU_op(o_alu_op),
      .C0(C0),
      .C1(C1),
      .C2(C2),
      .C3(C3),
      .C4(C4),
      .C5(C5),
      .C6(C6),
      .C7(C7),
      .C8(C8),
      .C9(C9),
      .C10(C10),
      .C11(C11),
      .C12(C12),
      .C13(C13),
      .C14(C14),
      .C15(C15)
  );


  // Assignments

  assign o_IF_stage = C2;

endmodule

designs/control_unit/cu_tb.v
`timescale 1ns / 1ps

module tb_CU_TOP;

  // Inputs to the DUT (Device Under Test)
  reg i_clk;
  reg i_rst_n;
  reg [7:0] i_ir_data;
  reg [4:0] i_flags;  // ZF, CF, OF, NF, MF 

  // Outputs from the DUT
  wire [3:0] o_alu_op;
  wire o_ctrl_mar_increment;  // C23
  wire o_IF_stage;  // C2
  wire C0, C1, C2, C3, C4, C5, C6, C7, C8, C9, C10, C11, C12, C13, C14, C15;

  // Instantiate the CU_TOP module
  CU_TOP uut (
      .i_clk(i_clk),
      .i_rst_n(i_rst_n),
      .i_flags(i_flags),
      .i_ir_data(i_ir_data),
      .o_alu_op(o_alu_op),
      .o_ctrl_halt(),
      .o_ctrl_mar_increment(o_ctrl_mar_increment),
      .o_IF_stage(o_IF_stage),
      .C0(C0),
      .C1(C1),
      .C2(C2),
      .C3(C3),
      .C4(C4),
      .C5(C5),
      .C6(C6),
      .C7(C7),
      .C8(C8),
      .C9(C9),
      .C10(C10),
      .C11(C11),
      .C12(C12),
      .C13(C13),
      .C14(C14),
      .C15(C15)
  );

  // Clock generation
  always begin
    #5 i_clk = ~i_clk;  // Period = 10 ns, 100 MHz clock
  end

  // Initial block for stimulus
  initial begin
    // Initialize signals
    i_clk = 0;
    i_rst_n = 0;  // Apply reset
    i_ir_data = 8'b0;
    i_flags = 5'b0;

    // Apply reset for some time
    #10 i_rst_n = 1;  // Release reset after 10 ns

    // Test 1: Provide test input and observe outputs
    #20 i_ir_data = 8'h1A;  // Some instruction value
    i_flags = 5'b10100;  // Set specific flags (e.g., ZF, NF, MF)

    // Test 2: Change instruction data
    #30 i_ir_data = 8'h2B;  // Another instruction value
    i_flags = 5'b01010;  // Change flags

    // Test 3: Provide another test case
    #40 i_ir_data = 8'h3C;
    i_flags = 5'b11001;  // Change flags again

    // Test 4: Test with other specific values
    #50 i_ir_data = 8'hFF;  // All ones as test instruction
    i_flags = 5'b00001;  // Set flags

    // Finish the simulation after some tests
    #100 $finish;
  end

  // Monitor the outputs
  initial begin
    $dumpfile("cu_top_tb.vcd");
    $dumpvars(0, tb_CU_TOP);
  end

endmodule

designs/control_unit/cu_top_tb.vcd
$date
	Fri Apr 25 00:41:01 2025
$end
$version
	Icarus Verilog
$end
$timescale
	1ps
$end
$scope module tb_CU_TOP $end
$var wire 1 ! o_ctrl_mar_increment $end
$var wire 4 " o_alu_op [3:0] $end
$var wire 1 # o_IF_stage $end
$var wire 1 $ C9 $end
$var wire 1 % C8 $end
$var wire 1 & C7 $end
$var wire 1 ' C6 $end
$var wire 1 ( C5 $end
$var wire 1 ) C4 $end
$var wire 1 * C3 $end
$var wire 1 + C2 $end
$var wire 1 , C15 $end
$var wire 1 - C14 $end
$var wire 1 . C13 $end
$var wire 1 / C12 $end
$var wire 1 0 C11 $end
$var wire 1 1 C10 $end
$var wire 1 2 C1 $end
$var wire 1 3 C0 $end
$var reg 1 4 i_clk $end
$var reg 5 5 i_flags [4:0] $end
$var reg 8 6 i_ir_data [7:0] $end
$var reg 1 7 i_rst_n $end
$scope module uut $end
$var wire 1 4 i_clk $end
$var wire 5 8 i_flags [4:0] $end
$var wire 8 9 i_ir_data [7:0] $end
$var wire 1 7 i_rst_n $end
$var wire 1 # o_IF_stage $end
$var wire 1 ! o_ctrl_mar_increment $end
$var wire 1 : o_ctrl_halt $end
$var wire 4 ; o_alu_op [3:0] $end
$var wire 2 < next_addr [1:0] $end
$var wire 24 = control_word [23:0] $end
$var wire 7 > car_data [6:0] $end
$var wire 1 $ C9 $end
$var wire 1 % C8 $end
$var wire 1 & C7 $end
$var wire 1 ' C6 $end
$var wire 1 ( C5 $end
$var wire 1 ) C4 $end
$var wire 1 * C3 $end
$var wire 1 + C2 $end
$var wire 1 , C15 $end
$var wire 1 - C14 $end
$var wire 1 . C13 $end
$var wire 1 / C12 $end
$var wire 1 0 C11 $end
$var wire 1 1 C10 $end
$var wire 1 2 C1 $end
$var wire 1 3 C0 $end
$scope module control_CAR $end
$var wire 1 4 i_clk $end
$var wire 1 ? i_ctrl_MF $end
$var wire 1 @ i_ctrl_NF $end
$var wire 1 A i_ctrl_ZF $end
$var wire 5 B i_ir_data [4:0] $end
$var wire 1 7 i_rst_n $end
$var wire 4 C ir_data [3:0] $end
$var wire 1 D indirect_flag $end
$var wire 2 E i_control_word_car [1:0] $end
$var reg 1 F indirect_done $end
$var reg 7 G o_car_data [6:0] $end
$upscope $end
$scope module control_CBR $end
$var wire 2 H next_addr [1:0] $end
$var wire 24 I memory [23:0] $end
$var wire 1 ! ctrl_mar_increment $end
$var wire 1 : ctrl_global_halt $end
$var wire 1 $ C9 $end
$var wire 1 % C8 $end
$var wire 1 & C7 $end
$var wire 1 ' C6 $end
$var wire 1 ( C5 $end
$var wire 1 ) C4 $end
$var wire 1 * C3 $end
$var wire 1 + C2 $end
$var wire 1 , C15 $end
$var wire 1 - C14 $end
$var wire 1 . C13 $end
$var wire 1 / C12 $end
$var wire 1 0 C11 $end
$var wire 1 1 C10 $end
$var wire 1 2 C1 $end
$var wire 1 3 C0 $end
$var wire 4 J ALU_op [3:0] $end
$upscope $end
$scope module control_memory $end
$var wire 7 K car [6:0] $end
$var reg 24 L control_word [23:0] $end
$upscope $end
$upscope $end
$upscope $end
$enddefinitions $end
$comment Show the parameter values. $end
$dumpall
$end
#0
$dumpvars
b1000000000000000000100 L
b0 K
b0 J
b1000000000000000000100 I
b10 H
b0 G
0F
b10 E
0D
b0 C
b0 B
0A
0@
0?
b0 >
b1000000000000000000100 =
b10 <
b0 ;
0:
b0 9
b0 8
07
b0 6
b0 5
04
03
02
01
00
0/
0.
0-
0,
1+
0*
0)
0(
0'
0&
0%
0$
1#
b0 "
0!
$end
#5000
14
#10000
04
17
#15000
1(
0#
0+
13
b1000000000000000100001 =
b1000000000000000100001 I
b1000000000000000100001 L
b1 >
b1 G
b1 K
14
#20000
04
#25000
0(
1)
03
b1000000000000000010000 =
b1000000000000000010000 I
b1000000000000000010000 L
b10 >
b10 G
b10 K
14
#30000
b1010 C
1A
b1010 B
04
b10100 5
b10100 8
b11010 6
b11010 9
#35000
1-
0)
b1000000100000000000000 =
b1000000100000000000000 I
b1000000100000000000000 L
b11 >
b11 G
b11 K
14
#40000
04
#45000
b1 <
b1 E
b1 H
1,
0-
b100001000000000000000 =
b100001000000000000000 I
b100001000000000000000 L
b100 >
b100 G
b100 K
14
#50000
04
#55000
b10 <
b10 E
b10 H
b1100 "
b1100 ;
b1100 J
0,
1&
1'
b1011000000000011000000 =
b1011000000000011000000 I
b1011000000000011000000 L
b10111 >
b10111 G
b10111 K
14
#60000
b1011 C
0A
1@
b1011 B
04
b1010 5
b1010 8
b101011 6
b101011 9
#65000
b11 <
b11 E
b11 H
1$
0&
0'
b1111000000001000000000 =
b1111000000001000000000 I
b1111000000001000000000 L
b11000 >
b11000 G
b11000 K
14
#70000
04
#75000
b10 <
b10 E
b10 H
b0 "
b0 ;
b0 J
0$
1#
1+
b1000000000000000000100 =
b1000000000000000000100 I
b1000000000000000000100 L
b0 >
b0 G
b0 K
14
#80000
04
#85000
1(
0#
0+
13
b1000000000000000100001 =
b1000000000000000100001 I
b1000000000000000100001 L
b1 >
b1 G
b1 K
14
#90000
04
#95000
0(
1)
03
b1000000000000000010000 =
b1000000000000000010000 I
b1000000000000000010000 L
b10 >
b10 G
b10 K
14
#100000
b1100 C
1A
0@
1?
b1100 B
04
b11001 5
b11001 8
b111100 6
b111100 9
#105000
1-
0)
b1000000100000000000000 =
b1000000100000000000000 I
b1000000100000000000000 L
b11 >
b11 G
b11 K
14
#110000
04
#115000
b1 <
b1 E
b1 H
1,
0-
b100001000000000000000 =
b100001000000000000000 I
b100001000000000000000 L
b100 >
b100 G
b100 K
14
#120000
04
#125000
b10 <
b10 E
b10 H
b1110 "
b1110 ;
b1110 J
0,
1&
1'
b1011100000000011000000 =
b1011100000000011000000 I
b1011100000000011000000 L
b11011 >
b11011 G
b11011 K
14
#130000
04
#135000
b11 <
b11 E
b11 H
1$
0&
0'
b1111100000001000000000 =
b1111100000001000000000 I
b1111100000001000000000 L
b11100 >
b11100 G
b11100 K
14
#140000
04
#145000
b10 <
b10 E
b10 H
b0 "
b0 ;
b0 J
0$
1#
1+
b1000000000000000000100 =
b1000000000000000000100 I
b1000000000000000000100 L
b0 >
b0 G
b0 K
14
#150000
1D
b1111 C
0A
b11111 B
04
b1 5
b1 8
b11111111 6
b11111111 9
#155000
1)
0#
0+
b1000000000000000010000 =
b1000000000000000010000 I
b1000000000000000010000 L
1F
b10 >
b10 G
b10 K
14
#160000
04
#165000
1-
0)
b1000000100000000000000 =
b1000000100000000000000 I
b1000000100000000000000 L
b11 >
b11 G
b11 K
14
#170000
04
#175000
b1 <
b1 E
b1 H
1,
0-
b100001000000000000000 =
b100001000000000000000 I
b100001000000000000000 L
b100 >
b100 G
b100 K
14
#180000
04
#185000
b10 <
b10 E
b10 H
0,
1#
1+
b1000000000000000000100 =
b1000000000000000000100 I
b1000000000000000000100 L
b0 >
b0 G
b0 K
14
#190000
04
#195000
1(
0#
0+
13
b1000000000000000100001 =
b1000000000000000100001 I
b1000000000000000100001 L
b1 >
b1 G
b1 K
14
#200000
04
#205000
0(
1)
03
b1000000000000000010000 =
b1000000000000000010000 I
b1000000000000000010000 L
b10 >
b10 G
b10 K
14
#210000
04
#215000
1-
0)
b1000000100000000000000 =
b1000000100000000000000 I
b1000000100000000000000 L
b11 >
b11 G
b11 K
14
#220000
04
#225000
b1 <
b1 E
b1 H
1,
0-
b100001000000000000000 =
b100001000000000000000 I
b100001000000000000000 L
b100 >
b100 G
b100 K
14
#230000
04
#235000
b10 <
b10 E
b10 H
0,
1#
1+
b1000000000000000000100 =
b1000000000000000000100 I
b1000000000000000000100 L
b0 >
b0 G
b0 K
14
#240000
04
#245000
1(
0#
0+
13
b1000000000000000100001 =
b1000000000000000100001 I
b1000000000000000100001 L
b1 >
b1 G
b1 K
14
